open_data_contract_standard/__init__.py
open_data_contract_standard/model.py
open_data_contract_standard/py.typed
open_data_contract_standard/schema.json
open_data_contract_standard-3.1.1.dist-info/METADATA
open_data_contract_standard-3.1.1.dist-info/WHEEL
open_data_contract_standard-3.1.1.dist-info/licenses/LICENSE
open_data_contract_standard-3.1.1.dist-info/RECORD
