Metadata-Version: 2.4
Name: open-data-contract-standard
Version: 3.1.1
Summary: The Pydantic Model of the Open Data Contract Standard
Project-URL: Homepage, https://github.com/datacontract/open-data-contract-standard-python
Project-URL: Issues, https://github.com/datacontract/open-data-contract-standard-python/issues
Author-email: Jochen Christ <jochen.christ@innoq.com>, Stefan Negele <stefan.negele@innoq.com>, Simon Harrer <simon.harrer@innoq.com>
License-File: LICENSE
Classifier: License :: OSI Approved :: MIT License
Classifier: Operating System :: OS Independent
Classifier: Programming Language :: Python :: 3
Requires-Python: >=3.10
Requires-Dist: pydantic>=2.8.0
Requires-Dist: pyyaml>=6.0.0
Provides-Extra: dev
Requires-Dist: pytest; extra == 'dev'
Requires-Dist: ruff; extra == 'dev'
